[
    {
        "elevation": 228.9,
        "mindate": "1893-01-01",
        "maxdate": "1978-09-30",
        "latitude": 42.65,
        "name": "ADAMS, MA US",
        "datacoverage": 0.6557,
        "id": "GHCND:USC00190049",
        "elevationUnit": "METERS",
        "longitude": -73.1
    },
    {
        "elevation": 44.2,
        "mindate": "1893-01-01",
        "maxdate": "2025-02-25",
        "latitude": 42.3861,
        "name": "AMHERST, MA US",
        "datacoverage": 0.9841,
        "id": "GHCND:USC00190120",
        "elevationUnit": "METERS",
        "longitude": -72.5374
    },
    {
        "elevation": 84.1,
        "mindate": "1890-01-01",
        "maxdate": "1897-08-31",
        "latitude": 42.65,
        "name": "ANDOVER, MA US",
        "datacoverage": 0.6818,
        "id": "GHCND:USC00190130",
        "elevationUnit": "METERS",
        "longitude": -71.133333
    },
    {
        "elevation": 54.9,
        "mindate": "1943-01-01",
        "maxdate": "1950-01-31",
        "latitude": 42.41667,
        "name": "ARLINGTON, MA US",
        "datacoverage": 1,
        "id": "GHCND:USC00190166",
        "elevationUnit": "METERS",
        "longitude": -71.18333
    },
    {
        "elevation": 337.7,
        "mindate": "1906-06-01",
        "maxdate": "2025-02-25",
        "latitude": 42.6178,
        "name": "ASHBURNHAM, MA US",
        "datacoverage": 0.7004,
        "id": "GHCND:USC00190190",
        "elevationUnit": "METERS",
        "longitude": -71.9159
    },
    {
        "elevation": 349.3,
        "mindate": "2003-10-01",
        "maxdate": "2025-02-24",
        "latitude": 42.6617,
        "name": "ASHBURNHAM NORTH, MA US",
        "datacoverage": 0.9446,
        "id": "GHCND:USC00190192",
        "elevationUnit": "METERS",
        "longitude": -71.9359
    },
    {
        "elevation": 408.4,
        "mindate": "1978-04-01",
        "maxdate": "2011-01-31",
        "latitude": 42.5134,
        "name": "ASHFIELD, MA US",
        "datacoverage": 0.9921,
        "id": "GHCND:USC00190213",
        "elevationUnit": "METERS",
        "longitude": -72.8507
    },
    {
        "elevation": 294.1,
        "mindate": "2012-05-01",
        "maxdate": "2016-04-21",
        "latitude": 42.5457,
        "name": "ASHFIELD 2 NE, MA US",
        "datacoverage": 0.969,
        "id": "GHCND:USC00190214",
        "elevationUnit": "METERS",
        "longitude": -72.7802
    },
    {
        "elevation": 57,
        "mindate": "1905-11-01",
        "maxdate": "1925-07-31",
        "latitude": 42.1,
        "name": "BAKER S BRIDGE, MA US",
        "datacoverage": 0.9881,
        "id": "GHCND:USC00190360",
        "elevationUnit": "METERS",
        "longitude": -71.333333
    },
    {
        "elevation": 251.5,
        "mindate": "1959-02-01",
        "maxdate": "2025-02-25",
        "latitude": 42.428,
        "name": "BARRE FALLS DAM, MA US",
        "datacoverage": 0.9579,
        "id": "GHCND:USC00190408",
        "elevationUnit": "METERS",
        "longitude": -72.0275
    },
    {
        "elevation": 485.2,
        "mindate": "1973-07-01",
        "maxdate": "1987-12-31",
        "latitude": 42.31667,
        "name": "BECKET 2 SW, MA US",
        "datacoverage": 0.9377,
        "id": "GHCND:USC00190510",
        "elevationUnit": "METERS",
        "longitude": -73.11667
    },
    {
        "elevation": 48.8,
        "mindate": "1957-05-01",
        "maxdate": "2009-04-30",
        "latitude": 42.48333,
        "name": "BEDFORD, MA US",
        "datacoverage": 0.9931,
        "id": "GHCND:USC00190535",
        "elevationUnit": "METERS",
        "longitude": -71.28333
    },
    {
        "elevation": 48.8,
        "mindate": "1893-04-01",
        "maxdate": "1923-09-30",
        "latitude": 42.466667,
        "name": "BEDFORD, MA US",
        "datacoverage": 0.9761,
        "id": "GHCND:USC00190538",
        "elevationUnit": "METERS",
        "longitude": -71.25
    },
    {
        "elevation": 167.6,
        "mindate": "1942-01-01",
        "maxdate": "2025-02-24",
        "latitude": 42.2796,
        "name": "BELCHERTOWN, MA US",
        "datacoverage": 0.9924,
        "id": "GHCND:USC00190562",
        "elevationUnit": "METERS",
        "longitude": -72.3482
    },
    {
        "mindate": "1901-11-01",
        "maxdate": "1905-11-30",
        "latitude": 42.4,
        "name": "BELMONT, MA US",
        "datacoverage": 0.9182,
        "id": "GHCND:USC00190582",
        "longitude": -71.15
    },
    {
        "elevation": 19.8,
        "mindate": "1996-06-01",
        "maxdate": "2025-02-25",
        "latitude": 42.588,
        "name": "BEVERLY, MA US",
        "datacoverage": 0.9549,
        "id": "GHCND:USC00190593",
        "elevationUnit": "METERS",
        "longitude": -70.8371
    },
    {
        "elevation": 23.8,
        "mindate": "1885-06-01",
        "maxdate": "1896-10-31",
        "latitude": 42.566667,
        "name": "BEVERLY FARMS, MA US",
        "datacoverage": 0.5838,
        "id": "GHCND:USC00190595",
        "elevationUnit": "METERS",
        "longitude": -70.816667
    },
    {
        "elevation": 43,
        "mindate": "1948-08-01",
        "maxdate": "1950-07-31",
        "latitude": 42.56667,
        "name": "BILLERICA, MA US",
        "datacoverage": 0.9945,
        "id": "GHCND:USC00190655",
        "elevationUnit": "METERS",
        "longitude": -71.26667
    },
    {
        "elevation": 260.6,
        "mindate": "1948-06-01",
        "maxdate": "2025-02-25",
        "latitude": 42.6324,
        "name": "BIRCH HILL DAM, MA US",
        "datacoverage": 0.9397,
        "id": "GHCND:USC00190666",
        "elevationUnit": "METERS",
        "longitude": -72.1227
    },
    {
        "elevation": 190.5,
        "mindate": "1893-01-01",
        "maxdate": "2025-02-25",
        "latitude": 42.2123,
        "name": "BLUE HILL COOP, MA US",
        "datacoverage": 0.998,
        "id": "GHCND:USC00190736",
        "elevationUnit": "METERS",
        "longitude": -71.1137
    },
    {
        "elevation": 338.3,
        "mindate": "1969-05-01",
        "maxdate": "1995-05-31",
        "latitude": 42.13333,
        "name": "BORDEN BROOK RSVR, MA US",
        "datacoverage": 0.9585,
        "id": "GHCND:USC00190759",
        "elevationUnit": "METERS",
        "longitude": -72.93333
    },
    {
        "elevation": 13.1,
        "mindate": "1889-01-01",
        "maxdate": "1889-12-31",
        "latitude": 41.783333,
        "name": "BREWSTER, MA US",
        "datacoverage": 1,
        "id": "GHCND:USC00190830",
        "elevationUnit": "METERS",
        "longitude": -70.033333
    },
    {
        "elevation": 12.2,
        "mindate": "2007-05-01",
        "maxdate": "2025-02-25",
        "latitude": 41.9538,
        "name": "BRIDGEWATER, MA US",
        "datacoverage": 0.9754,
        "id": "GHCND:USC00190840",
        "elevationUnit": "METERS",
        "longitude": -70.9571
    },
    {
        "elevation": 22.9,
        "mindate": "1894-01-01",
        "maxdate": "2025-02-22",
        "latitude": 42.04756,
        "name": "BROCKTON, MA US",
        "datacoverage": 0.8856,
        "id": "GHCND:USC00190860",
        "elevationUnit": "METERS",
        "longitude": -71.00819
    },
    {
        "elevation": 158.5,
        "mindate": "1959-05-01",
        "maxdate": "2025-02-25",
        "latitude": 42.1163,
        "name": "BUFFUMVILLE LAKE, MA US",
        "datacoverage": 0.9204,
        "id": "GHCND:USC00190998",
        "elevationUnit": "METERS",
        "longitude": -71.9074
    },
    {
        "elevation": 18,
        "mindate": "1884-11-01",
        "maxdate": "1951-08-31",
        "latitude": 42.38333,
        "name": "CAMBRIDGE, MA US",
        "datacoverage": 0.3424,
        "id": "GHCND:USC00191097",
        "elevationUnit": "METERS",
        "longitude": -71.11667
    },
    {
        "elevation": 2.4,
        "mindate": "1890-01-01",
        "maxdate": "1896-06-30",
        "latitude": 42.383333,
        "name": "CAMBRIDGE B, MA US",
        "datacoverage": 1,
        "id": "GHCND:USC00191099",
        "elevationUnit": "METERS",
        "longitude": -71.1
    },
    {
        "elevation": 4,
        "mindate": "1931-01-01",
        "maxdate": "1932-03-31",
        "latitude": 42.375097,
        "name": "CAMBRIDGE C, MA US",
        "datacoverage": 0.932,
        "id": "GHCND:USC00191103",
        "elevationUnit": "METERS",
        "longitude": -71.105608
    },
    {
        "elevation": 5.8,
        "mindate": "1931-04-01",
        "maxdate": "1934-01-31",
        "latitude": 42.366667,
        "name": "CAMBRIDGE MIT, MA US",
        "datacoverage": 0.9961,
        "id": "GHCND:USC00191110",
        "elevationUnit": "METERS",
        "longitude": -71.1
    },
    {
        "elevation": 14.9,
        "mindate": "1963-07-01",
        "maxdate": "1966-04-30",
        "latitude": 41.9,
        "name": "SOUTH WELLFLEET, MA US",
        "datacoverage": 1,
        "id": "GHCND:USC00191147",
        "elevationUnit": "METERS",
        "longitude": -69.98333
    },
    {
        "elevation": 267.9,
        "mindate": "1951-09-01",
        "maxdate": "1952-09-30",
        "latitude": 42.13333,
        "name": "CHARLTON, MA US",
        "datacoverage": 0.9975,
        "id": "GHCND:USC00191343",
        "elevationUnit": "METERS",
        "longitude": -71.96667
    },
    {
        "elevation": 207,
        "mindate": "1953-01-01",
        "maxdate": "1956-11-30",
        "latitude": 42.13333,
        "name": "CHARLTON 2, MA US",
        "datacoverage": 1,
        "id": "GHCND:USC00191344",
        "elevationUnit": "METERS",
        "longitude": -71.95
    },
    {
        "elevation": 299,
        "mindate": "1957-03-01",
        "maxdate": "1958-12-30",
        "latitude": 42.13333,
        "name": "CHARLTON MASONIC HM, MA US",
        "datacoverage": 0.8522,
        "id": "GHCND:USC00191345",
        "elevationUnit": "METERS",
        "longitude": -71.96667
    },
    {
        "elevation": 12.2,
        "mindate": "1972-08-01",
        "maxdate": "2021-03-31",
        "latitude": 41.657,
        "name": "CHATHAM, MA US",
        "datacoverage": 0.9609,
        "id": "GHCND:USC00191386",
        "elevationUnit": "METERS",
        "longitude": -69.9592
    },
    {
        "elevation": 195.1,
        "mindate": "1925-04-01",
        "maxdate": "1957-04-30",
        "latitude": 42.3,
        "name": "CHESTER 2, MA US",
        "datacoverage": 0.9814,
        "id": "GHCND:USC00191425",
        "elevationUnit": "METERS",
        "longitude": -72.98333
    },
    {
        "elevation": 195.1,
        "mindate": "1962-12-01",
        "maxdate": "1988-12-31",
        "latitude": 42.3,
        "name": "CHESTER 2, MA US",
        "datacoverage": 0.911,
        "id": "GHCND:USC00191430",
        "elevationUnit": "METERS",
        "longitude": -72.98333
    },
    {
        "elevation": 36.9,
        "mindate": "1893-01-01",
        "maxdate": "1986-04-30",
        "latitude": 42.33333,
        "name": "CHESTNUT HILL, MA US",
        "datacoverage": 0.9872,
        "id": "GHCND:USC00191447",
        "elevationUnit": "METERS",
        "longitude": -71.15
    },
    {
        "elevation": 121.9,
        "mindate": "1896-10-01",
        "maxdate": "1985-12-31",
        "latitude": 42.4,
        "name": "CLINTON, MA US",
        "datacoverage": 0.8032,
        "id": "GHCND:USC00191561",
        "elevationUnit": "METERS",
        "longitude": -71.68333
    },
    {
        "elevation": 85.3,
        "mindate": "1893-01-01",
        "maxdate": "1907-12-31",
        "latitude": 42.416667,
        "name": "CLINTON B, MA US",
        "datacoverage": 0.6022,
        "id": "GHCND:USC00191563",
        "elevationUnit": "METERS",
        "longitude": -71.683333
    },
    {
        "elevation": 14.9,
        "mindate": "1895-07-01",
        "maxdate": "1960-09-08",
        "latitude": 42.23333,
        "name": "COHASSET, MA US",
        "datacoverage": 0.3004,
        "id": "GHCND:USC00191582",
        "elevationUnit": "METERS",
        "longitude": -70.8
    },
    {
        "elevation": 207,
        "mindate": "1942-01-01",
        "maxdate": "1959-07-31",
        "latitude": 42.38333,
        "name": "COLDBROOK, MA US",
        "datacoverage": 0.9537,
        "id": "GHCND:USC00191589",
        "elevationUnit": "METERS",
        "longitude": -72.05
    },
    {
        "elevation": 43,
        "mindate": "1893-01-01",
        "maxdate": "1950-08-31",
        "latitude": 42.45,
        "name": "CONCORD, MA US",
        "datacoverage": 0.8121,
        "id": "GHCND:USC00191622",
        "elevationUnit": "METERS",
        "longitude": -71.36667
    },
    {
        "elevation": 18.3,
        "mindate": "1885-01-01",
        "maxdate": "1892-08-31",
        "latitude": 41.616667,
        "name": "COTUIT, MA US",
        "datacoverage": 0.9454,
        "id": "GHCND:USC00191650",
        "elevationUnit": "METERS",
        "longitude": -70.433333
    },
    {
        "elevation": 426.7,
        "mindate": "1903-04-01",
        "maxdate": "1907-06-30",
        "latitude": 42.5,
        "name": "CUMMINGTON, MA US",
        "datacoverage": 1,
        "id": "GHCND:USC00191770",
        "elevationUnit": "METERS",
        "longitude": -72.9
    },
    {
        "elevation": 490.7,
        "mindate": "1963-05-15",
        "maxdate": "1994-01-31",
        "latitude": 42.46667,
        "name": "CUMMINGTON HILL, MA US",
        "datacoverage": 0.9878,
        "id": "GHCND:USC00191774",
        "elevationUnit": "METERS",
        "longitude": -72.93333
    },
    {
        "elevation": 365.8,
        "mindate": "1885-01-01",
        "maxdate": "1887-12-31",
        "latitude": 42.466667,
        "name": "DALTON, MA US",
        "datacoverage": 0.9708,
        "id": "GHCND:USC00191820",
        "elevationUnit": "METERS",
        "longitude": -73.166667
    },
    {
        "elevation": 369.4,
        "mindate": "1996-09-01",
        "maxdate": "2012-03-31",
        "latitude": 42.4686,
        "name": "DALTON, MA US",
        "datacoverage": 0.8227,
        "id": "GHCND:USC00191821",
        "elevationUnit": "METERS",
        "longitude": -73.1531
    },
    {
        "elevation": 15.2,
        "mindate": "1898-05-01",
        "maxdate": "1918-09-30",
        "latitude": 42.283333,
        "name": "DORCHESTER, MA US",
        "datacoverage": 0.2687,
        "id": "GHCND:USC00191950",
        "elevationUnit": "METERS",
        "longitude": -71.066667
    },
    {
        "elevation": 82,
        "mindate": "1971-01-01",
        "maxdate": "1978-06-30",
        "latitude": 42.7,
        "name": "DRACUT, MA US",
        "datacoverage": 0.9945,
        "id": "GHCND:USC00191992",
        "elevationUnit": "METERS",
        "longitude": -71.28333
    },
    {
        "elevation": 493.2,
        "mindate": "1932-01-01",
        "maxdate": "1934-04-30",
        "latitude": 42.652306,
        "name": "DRURY, MA US",
        "datacoverage": 0.3831,
        "id": "GHCND:USC00192000",
        "elevationUnit": "METERS",
        "longitude": -72.9976
    },
    {
        "elevation": 213.4,
        "mindate": "1885-01-01",
        "maxdate": "1900-05-31",
        "latitude": 42.033333,
        "name": "DUDLEY, MA US",
        "datacoverage": 0.9428,
        "id": "GHCND:USC00192010",
        "elevationUnit": "METERS",
        "longitude": -71.933333
    },
    {
        "elevation": 64,
        "mindate": "1970-06-01",
        "maxdate": "1990-06-30",
        "latitude": 42.66667,
        "name": "PEPPERELL, MA US",
        "datacoverage": 0.9915,
        "id": "GHCND:USC00192026",
        "elevationUnit": "METERS",
        "longitude": -71.53333
    },
    {
        "elevation": 213.4,
        "mindate": "1962-06-01",
        "maxdate": "2025-02-25",
        "latitude": 42.1103,
        "name": "EAST BRIMFIELD LAKE, MA US",
        "datacoverage": 0.9499,
        "id": "GHCND:USC00192107",
        "elevationUnit": "METERS",
        "longitude": -72.1269
    },
    {
        "elevation": 4.6,
        "mindate": "1930-04-01",
        "maxdate": "1946-10-31",
        "latitude": 42.616667,
        "name": "EAST GLOUCESTER, MA US",
        "datacoverage": 0.9949,
        "id": "GHCND:USC00192150",
        "elevationUnit": "METERS",
        "longitude": -70.65
    },
    {
        "elevation": 502,
        "mindate": "2015-08-06",
        "maxdate": "2025-02-21",
        "latitude": 42.5742,
        "name": "EAST HAWLEY, MA US",
        "datacoverage": 0.9811,
        "id": "GHCND:USC00192175",
        "elevationUnit": "METERS",
        "longitude": -72.868
    },
    {
        "elevation": 45.7,
        "mindate": "2009-10-08",
        "maxdate": "2025-02-25",
        "latitude": 41.7145,
        "name": "EAST SANDWICH, MA US",
        "datacoverage": 0.99,
        "id": "GHCND:USC00192372",
        "elevationUnit": "METERS",
        "longitude": -70.4718
    },
    {
        "elevation": 365.8,
        "mindate": "1893-08-01",
        "maxdate": "1906-08-31",
        "latitude": 42.55,
        "name": "EAST TEMPLETON, MA US",
        "datacoverage": 0.9763,
        "id": "GHCND:USC00192420",
        "elevationUnit": "METERS",
        "longitude": -72
    },
    {
        "elevation": 9.1,
        "mindate": "1912-04-26",
        "maxdate": "2025-02-05",
        "latitude": 41.7653,
        "name": "EAST WAREHAM, MA US",
        "datacoverage": 0.8996,
        "id": "GHCND:USC00192451",
        "elevationUnit": "METERS",
        "longitude": -70.6697
    },
    {
        "elevation": 9.1,
        "mindate": "1946-03-01",
        "maxdate": "2025-02-13",
        "latitude": 41.3854,
        "name": "EDGARTOWN, MA US",
        "datacoverage": 0.9958,
        "id": "GHCND:USC00192501",
        "elevationUnit": "METERS",
        "longitude": -70.518
    },
    {
        "elevation": 57.9,
        "mindate": "1893-01-01",
        "maxdate": "1976-04-18",
        "latitude": 41.71667,
        "name": "FALL RIVER, MA US",
        "datacoverage": 0.9874,
        "id": "GHCND:USC00192642",
        "elevationUnit": "METERS",
        "longitude": -71.13333
    },
    {
        "elevation": 100.9,
        "mindate": "1893-01-01",
        "maxdate": "1978-12-31",
        "latitude": 42.55,
        "name": "FITCHBURG 4 SE, MA US",
        "datacoverage": 0.9938,
        "id": "GHCND:USC00192806",
        "elevationUnit": "METERS",
        "longitude": -71.75
    },
    {
        "elevation": 202.7,
        "mindate": "2016-08-09",
        "maxdate": "2025-02-07",
        "latitude": 42.6168,
        "name": "FITCHBURG COOP, MA US",
        "datacoverage": 0.9942,
        "id": "GHCND:USC00192807",
        "elevationUnit": "METERS",
        "longitude": -71.8017
    },
    {
        "elevation": 160,
        "mindate": "1897-04-06",
        "maxdate": "1901-12-31",
        "latitude": 42.566667,
        "name": "FITCHBURG C, MA US",
        "datacoverage": 0.93,
        "id": "GHCND:USC00192812",
        "elevationUnit": "METERS",
        "longitude": -71.8
    },
    {
        "mindate": "1891-01-06",
        "maxdate": "1896-02-29",
        "latitude": 42.666667,
        "name": "FLORIDA, MA US",
        "datacoverage": 0.2631,
        "id": "GHCND:USC00192850",
        "longitude": -73.033333
    },
    {
        "elevation": 82.3,
        "mindate": "2009-11-01",
        "maxdate": "2019-12-31",
        "latitude": 42.0785,
        "name": "FOXBORO, MA US",
        "datacoverage": 0.9806,
        "id": "GHCND:USC00192913",
        "elevationUnit": "METERS",
        "longitude": -71.238
    },
    {
        "elevation": 52.1,
        "mindate": "1893-01-01",
        "maxdate": "1989-11-30",
        "latitude": 42.28333,
        "name": "FRAMINGHAM, MA US",
        "datacoverage": 0.9841,
        "id": "GHCND:USC00192975",
        "elevationUnit": "METERS",
        "longitude": -71.41667
    },
    {
        "elevation": 15.2,
        "mindate": "1885-06-01",
        "maxdate": "1895-09-30",
        "latitude": 42.283333,
        "name": "GILBERTVILLE, MA US",
        "datacoverage": 0.8863,
        "id": "GHCND:USC00193110",
        "elevationUnit": "METERS",
        "longitude": -72.216667
    },
    {
        "elevation": 374.9,
        "mindate": "1986-05-01",
        "maxdate": "1990-08-31",
        "latitude": 42.06667,
        "name": "GRANVILLE, MA US",
        "datacoverage": 1,
        "id": "GHCND:USC00193167",
        "elevationUnit": "METERS",
        "longitude": -72.9
    },
    {
        "elevation": 209.7,
        "mindate": "1893-02-01",
        "maxdate": "1973-12-31",
        "latitude": 42.21667,
        "name": "GREAT BARRINGTON, MA US",
        "datacoverage": 0.1767,
        "id": "GHCND:USC00193208",
        "elevationUnit": "METERS",
        "longitude": -73.35
    },
    {
        "elevation": 209.7,
        "mindate": "1973-12-01",
        "maxdate": "2014-03-30",
        "latitude": 42.2167,
        "name": "GREAT BARRINGTON 2 N, MA US",
        "datacoverage": 0.7415,
        "id": "GHCND:USC00193213",
        "elevationUnit": "METERS",
        "longitude": -73.35
    },
    {
        "elevation": 56.4,
        "mindate": "1929-03-01",
        "maxdate": "1946-06-30",
        "latitude": 42.583333,
        "name": "GREENFIELD, MA US",
        "datacoverage": 0.9608,
        "id": "GHCND:USC00193224",
        "elevationUnit": "METERS",
        "longitude": -72.6
    },
    {
        "elevation": 39.6,
        "mindate": "2005-09-01",
        "maxdate": "2025-02-25",
        "latitude": 42.5719,
        "name": "GREENFIELD NUMBER 3, MA US",
        "datacoverage": 0.9874,
        "id": "GHCND:USC00193229",
        "elevationUnit": "METERS",
        "longitude": -72.5975
    },
    {
        "elevation": 103.9,
        "mindate": "1893-01-01",
        "maxdate": "1974-04-30",
        "latitude": 42.6,
        "name": "GROTON, MA US",
        "datacoverage": 0.7655,
        "id": "GHCND:USC00193270",
        "elevationUnit": "METERS",
        "longitude": -71.58333
    },
    {
        "elevation": 9.1,
        "mindate": "1992-08-01",
        "maxdate": "2025-02-24",
        "latitude": 42.7467,
        "name": "GROVELAND, MA US",
        "datacoverage": 0.9993,
        "id": "GHCND:USC00193276",
        "elevationUnit": "METERS",
        "longitude": -71.0426
    },
    {
        "elevation": 41.1,
        "mindate": "1893-09-01",
        "maxdate": "1899-10-31",
        "latitude": 42.5,
        "name": "HADLEY, MA US",
        "datacoverage": 0.6483,
        "id": "GHCND:USC00193295",
        "elevationUnit": "METERS",
        "longitude": -72.583333
    },
    {
        "elevation": 27.1,
        "mindate": "1912-04-15",
        "maxdate": "1943-10-15",
        "latitude": 42.01667,
        "name": "HALIFAX, MA US",
        "datacoverage": 0.0627,
        "id": "GHCND:USC00193304",
        "elevationUnit": "METERS",
        "longitude": -70.88333
    },
    {
        "elevation": 6.1,
        "mindate": "1899-11-01",
        "maxdate": "2025-01-31",
        "latitude": 42.7594,
        "name": "HAVERHILL, MA US",
        "datacoverage": 0.9547,
        "id": "GHCND:USC00193505",
        "elevationUnit": "METERS",
        "longitude": -71.0602
    },
    {
        "elevation": 10.7,
        "mindate": "1960-09-01",
        "maxdate": "2025-02-24",
        "latitude": 42.2269,
        "name": "HINGHAM, MA US",
        "datacoverage": 0.9971,
        "id": "GHCND:USC00193624",
        "elevationUnit": "METERS",
        "longitude": -70.9125
    },
    {
        "elevation": 67.1,
        "mindate": "1894-12-01",
        "maxdate": "1934-01-31",
        "latitude": 42.366667,
        "name": "HOBBS BROOK, MA US",
        "datacoverage": 0.6906,
        "id": "GHCND:USC00193640",
        "elevationUnit": "METERS",
        "longitude": -71.333333
    },
    {
        "elevation": 259.1,
        "mindate": "1931-01-01",
        "maxdate": "1934-02-28",
        "latitude": 42.35,
        "name": "HOLDEN, MA US",
        "datacoverage": 0.9853,
        "id": "GHCND:USC00193690",
        "elevationUnit": "METERS",
        "longitude": -71.85
    },
    {
        "elevation": 61,
        "mindate": "1924-04-18",
        "maxdate": "1925-10-15",
        "latitude": 42.2,
        "name": "HOLLISTON, MA US",
        "datacoverage": 0.4707,
        "id": "GHCND:USC00193695",
        "elevationUnit": "METERS",
        "longitude": -71.433333
    },
    {
        "elevation": 29.9,
        "mindate": "1902-11-01",
        "maxdate": "2006-12-31",
        "latitude": 42.2,
        "name": "HOLYOKE, MA US",
        "datacoverage": 0.8841,
        "id": "GHCND:USC00193702",
        "elevationUnit": "METERS",
        "longitude": -72.6
    },
    {
        "elevation": 244.1,
        "mindate": "1930-05-01",
        "maxdate": "1973-06-30",
        "latitude": 42.68333,
        "name": "HOOSAC TUNNEL, MA US",
        "datacoverage": 0.9901,
        "id": "GHCND:USC00193713",
        "elevationUnit": "METERS",
        "longitude": -72.96667
    },
    {
        "elevation": 299,
        "mindate": "1925-04-01",
        "maxdate": "1980-10-31",
        "latitude": 42.48333,
        "name": "HUBBARDSTON, MA US",
        "datacoverage": 0.988,
        "id": "GHCND:USC00193772",
        "elevationUnit": "METERS",
        "longitude": -72
    },
    {
        "elevation": 18.3,
        "mindate": "1893-01-01",
        "maxdate": "2025-02-25",
        "latitude": 41.6649,
        "name": "HYANNIS, MA US",
        "datacoverage": 0.8312,
        "id": "GHCND:USC00193821",
        "elevationUnit": "METERS",
        "longitude": -70.3038
    },
    {
        "elevation": 29,
        "mindate": "1962-08-15",
        "maxdate": "2025-02-25",
        "latitude": 42.30298,
        "name": "JAMAICA PLAIN, MA US",
        "datacoverage": 0.9187,
        "id": "GHCND:USC00193890",
        "elevationUnit": "METERS",
        "longitude": -71.12415
    },
    {
        "mindate": "1890-01-01",
        "maxdate": "1894-09-30",
        "latitude": 42.366667,
        "name": "KENDALL GREEN, MA US",
        "datacoverage": 0.9371,
        "id": "GHCND:USC00193940",
        "longitude": -71.283333
    },
    {
        "elevation": 36.3,
        "mindate": "1931-01-01",
        "maxdate": "1945-12-31",
        "latitude": 42.8,
        "name": "KENOZA LAKE, MA US",
        "datacoverage": 0.9995,
        "id": "GHCND:USC00193946",
        "elevationUnit": "METERS",
        "longitude": -71.05
    },
    {
        "elevation": 192,
        "mindate": "1948-06-01",
        "maxdate": "1997-06-30",
        "latitude": 42.28333,
        "name": "KNIGHTVILLE DAM, MA US",
        "datacoverage": 0.9804,
        "id": "GHCND:USC00193985",
        "elevationUnit": "METERS",
        "longitude": -72.86667
    },
    {
        "elevation": 46,
        "mindate": "1885-01-01",
        "maxdate": "1960-09-30",
        "latitude": 42.31667,
        "name": "LAKE COCHITUATE, MA US",
        "datacoverage": 0.9124,
        "id": "GHCND:USC00194012",
        "elevationUnit": "METERS",
        "longitude": -71.38333
    },
    {
        "elevation": 376.7,
        "mindate": "1970-11-14",
        "maxdate": "1995-03-31",
        "latitude": 42.55,
        "name": "LANESBORO, MA US",
        "datacoverage": 0.9301,
        "id": "GHCND:USC00194075",
        "elevationUnit": "METERS",
        "longitude": -73.23333
    },
    {
        "elevation": 15.2,
        "mindate": "1893-01-01",
        "maxdate": "2025-02-23",
        "latitude": 42.6993,
        "name": "LAWRENCE, MA US",
        "datacoverage": 0.9893,
        "id": "GHCND:USC00194105",
        "elevationUnit": "METERS",
        "longitude": -71.1659
    },
    {
        "elevation": 118.9,
        "mindate": "1893-01-01",
        "maxdate": "1901-03-31",
        "latitude": 42.3,
        "name": "LEEDS, MA US",
        "datacoverage": 0.9777,
        "id": "GHCND:USC00194115",
        "elevationUnit": "METERS",
        "longitude": -72.666667
    },
    {
        "elevation": 309.1,
        "mindate": "1896-02-01",
        "maxdate": "1900-02-28",
        "latitude": 42.25,
        "name": "LEICESTER, MA US",
        "datacoverage": 0.959,
        "id": "GHCND:USC00194125",
        "elevationUnit": "METERS",
        "longitude": -71.916667
    },
    {
        "elevation": 306,
        "mindate": "1996-08-01",
        "maxdate": "2025-01-31",
        "latitude": 42.3356,
        "name": "LENOX DALE, MA US",
        "datacoverage": 0.966,
        "id": "GHCND:USC00194131",
        "elevationUnit": "METERS",
        "longitude": -73.2506
    },
    {
        "elevation": 96,
        "mindate": "2009-10-01",
        "maxdate": "2025-02-25",
        "latitude": 42.4468,
        "name": "LEVERETT NUMBER 2, MA US",
        "datacoverage": 0.9548,
        "id": "GHCND:USC00194154",
        "elevationUnit": "METERS",
        "longitude": -72.53
    },
    {
        "elevation": 61,
        "mindate": "1951-03-01",
        "maxdate": "1956-08-31",
        "latitude": 42.45,
        "name": "LEXINGTON, MA US",
        "datacoverage": 0.9806,
        "id": "GHCND:USC00194162",
        "elevationUnit": "METERS",
        "longitude": -71.2
    },
    {
        "elevation": 16.8,
        "mindate": "1885-01-01",
        "maxdate": "1890-12-31",
        "latitude": 41.733333,
        "name": "LONG PLAIN, MA US",
        "datacoverage": 0.9991,
        "id": "GHCND:USC00194295",
        "elevationUnit": "METERS",
        "longitude": -70.916667
    },
    {
        "elevation": 33.5,
        "mindate": "1885-08-01",
        "maxdate": "2025-02-25",
        "latitude": 42.6409,
        "name": "LOWELL, MA US",
        "datacoverage": 0.8584,
        "id": "GHCND:USC00194313",
        "elevationUnit": "METERS",
        "longitude": -71.3637
    },
    {
        "elevation": 115.8,
        "mindate": "1885-09-01",
        "maxdate": "1906-07-31",
        "latitude": 42.2,
        "name": "LUDLOW CENTER, MA US",
        "datacoverage": 0.9466,
        "id": "GHCND:USC00194340",
        "elevationUnit": "METERS",
        "longitude": -72.483333
    },
    {
        "elevation": 12.2,
        "mindate": "1885-10-01",
        "maxdate": "1900-03-31",
        "latitude": 42.466667,
        "name": "LYNN, MA US",
        "datacoverage": 0.8657,
        "id": "GHCND:USC00194360",
        "elevationUnit": "METERS",
        "longitude": -70.933333
    },
    {
        "mindate": "1885-05-01",
        "maxdate": "1887-10-31",
        "latitude": 42.575,
        "name": "MANCHESTER, MA US",
        "datacoverage": 0.6039,
        "id": "GHCND:USC00194405",
        "longitude": -70.74
    },
    {
        "elevation": 43,
        "mindate": "1893-01-02",
        "maxdate": "1986-03-31",
        "latitude": 42.05,
        "name": "MANSFIELD, MA US",
        "datacoverage": 0.6525,
        "id": "GHCND:USC00194449",
        "elevationUnit": "METERS",
        "longitude": -71.2
    },
    {
        "elevation": 25.6,
        "mindate": "1984-09-01",
        "maxdate": "2025-02-04",
        "latitude": 42.5007,
        "name": "MARBLEHEAD, MA US",
        "datacoverage": 0.9937,
        "id": "GHCND:USC00194502",
        "elevationUnit": "METERS",
        "longitude": -70.8644
    },
    {
        "elevation": 27.4,
        "mindate": "1912-04-01",
        "maxdate": "1952-10-16",
        "latitude": 41.683333,
        "name": "MARSTON MILLS, MA US",
        "datacoverage": 0.2514,
        "id": "GHCND:USC00194525",
        "elevationUnit": "METERS",
        "longitude": -70.433333
    },
    {
        "elevation": 62.5,
        "mindate": "1963-07-08",
        "maxdate": "2018-06-27",
        "latitude": 42.4293,
        "name": "MAYNARD 2, MA US",
        "datacoverage": 0.9292,
        "id": "GHCND:USC00194580",
        "elevationUnit": "METERS",
        "longitude": -71.4425
    },
    {
        "elevation": 13.7,
        "mindate": "1893-01-01",
        "maxdate": "2025-01-31",
        "latitude": 41.8819,
        "name": "MIDDLEBORO, MA US",
        "datacoverage": 0.8196,
        "id": "GHCND:USC00194711",
        "elevationUnit": "METERS",
        "longitude": -70.9085
    },
    {
        "elevation": 33.5,
        "mindate": "1925-11-01",
        "maxdate": "2025-02-25",
        "latitude": 42.5934,
        "name": "MIDDLETON, MA US",
        "datacoverage": 0.9964,
        "id": "GHCND:USC00194744",
        "elevationUnit": "METERS",
        "longitude": -71.0187
    },
    {
        "elevation": 85.3,
        "mindate": "1885-01-01",
        "maxdate": "2025-02-25",
        "latitude": 42.1633,
        "name": "MILFORD, MA US",
        "datacoverage": 0.6541,
        "id": "GHCND:USC00194760",
        "elevationUnit": "METERS",
        "longitude": -71.5119
    },
    {
        "elevation": 107,
        "mindate": "1930-05-01",
        "maxdate": "1960-03-31",
        "latitude": 42.18333,
        "name": "MILLBURY, MA US",
        "datacoverage": 0.9601,
        "id": "GHCND:USC00194771",
        "elevationUnit": "METERS",
        "longitude": -71.75
    },
    {
        "elevation": 30.5,
        "mindate": "1885-05-01",
        "maxdate": "1901-02-28",
        "latitude": 42.25,
        "name": "MILTON, MA US",
        "datacoverage": 0.9782,
        "id": "GHCND:USC00194795",
        "elevationUnit": "METERS",
        "longitude": -71.1
    },
    {
        "elevation": 566.9,
        "mindate": "1891-11-01",
        "maxdate": "1896-12-31",
        "latitude": 42.716667,
        "name": "MONROE, MA US",
        "datacoverage": 0.9688,
        "id": "GHCND:USC00194850",
        "elevationUnit": "METERS",
        "longitude": -72.983333
    },
    {
        "elevation": 128,
        "mindate": "1885-01-01",
        "maxdate": "1911-12-31",
        "latitude": 42.083333,
        "name": "MONSON, MA US",
        "datacoverage": 0.9563,
        "id": "GHCND:USC00194875",
        "elevationUnit": "METERS",
        "longitude": -72.333333
    },
    {
        "elevation": 61,
        "mindate": "1901-04-03",
        "maxdate": "1908-03-31",
        "latitude": 42.266667,
        "name": "MOUNT TOM, MA US",
        "datacoverage": 0.9425,
        "id": "GHCND:USC00195060",
        "elevationUnit": "METERS",
        "longitude": -72.633333
    },
    {
        "elevation": 27.4,
        "mindate": "1888-06-01",
        "maxdate": "1892-08-31",
        "latitude": 42.433333,
        "name": "NAHANT, MA ",
        "datacoverage": 0.7508,
        "id": "GHCND:USC00195145",
        "elevationUnit": "METERS",
        "longitude": -70.933333
    },
    {
        "elevation": 54.9,
        "mindate": "1978-04-01",
        "maxdate": "2014-07-12",
        "latitude": 42.2825,
        "name": "NATICK, MA US",
        "datacoverage": 0.9835,
        "id": "GHCND:USC00195175",
        "elevationUnit": "METERS",
        "longitude": -71.344
    },
    {
        "elevation": 5.5,
        "mindate": "1893-01-01",
        "maxdate": "2019-08-31",
        "latitude": 41.5954,
        "name": "NEW BEDFORD COOP, MA US",
        "datacoverage": 0.8236,
        "id": "GHCND:USC00195246",
        "elevationUnit": "METERS",
        "longitude": -70.9052
    },
    {
        "elevation": 16.8,
        "mindate": "1893-01-01",
        "maxdate": "1900-12-31",
        "latitude": 41.73333,
        "name": "NEW BEDFORD B, MA US",
        "datacoverage": 0.9812,
        "id": "GHCND:USC00195248",
        "elevationUnit": "METERS",
        "longitude": -70.91667
    },
    {
        "elevation": 16.8,
        "mindate": "1893-01-01",
        "maxdate": "2025-02-25",
        "latitude": 42.83203,
        "name": "NEWBURYPORT, MA US",
        "datacoverage": 0.7084,
        "id": "GHCND:USC00195285",
        "elevationUnit": "METERS",
        "longitude": -70.91518
    },
    {
        "elevation": 257.6,
        "mindate": "1897-03-01",
        "maxdate": "1998-12-31",
        "latitude": 42.45,
        "name": "NEW SALEM, MA US",
        "datacoverage": 0.5195,
        "id": "GHCND:USC00195306",
        "elevationUnit": "METERS",
        "longitude": -72.33333
    },
    {
        "elevation": 31.1,
        "mindate": "1887-10-15",
        "maxdate": "1954-08-31",
        "latitude": 42.3,
        "name": "NEWTON, MA US",
        "datacoverage": 0.2098,
        "id": "GHCND:USC00195317",
        "elevationUnit": "METERS",
        "longitude": -71.21667
    },
    {
        "elevation": 73.2,
        "mindate": "1903-01-01",
        "maxdate": "1915-11-30",
        "latitude": 42.133333,
        "name": "NORFOLK, MA US",
        "datacoverage": 0.9845,
        "id": "GHCND:USC00195390",
        "elevationUnit": "METERS",
        "longitude": -71.316667
    },
    {
        "elevation": 35.1,
        "mindate": "1893-01-01",
        "maxdate": "1910-12-31",
        "latitude": 42.6,
        "name": "NORTH BILLERICA, MA US",
        "datacoverage": 0.8643,
        "id": "GHCND:USC00195490",
        "elevationUnit": "METERS",
        "longitude": -71.3
    },
    {
        "elevation": 96,
        "mindate": "1964-02-01",
        "maxdate": "2025-02-22",
        "latitude": 42.11504,
        "name": "NORTHBRIDGE 2, MA US",
        "datacoverage": 0.991,
        "id": "GHCND:USC00195524",
        "elevationUnit": "METERS",
        "longitude": -71.676
    },
    {
        "elevation": 42.1,
        "mindate": "1886-10-01",
        "maxdate": "1954-08-31",
        "latitude": 42.03333,
        "name": "NORTH TRURO, MA US",
        "datacoverage": 0.1573,
        "id": "GHCND:USC00195891",
        "elevationUnit": "METERS",
        "longitude": -70.05
    },
    {
        "elevation": 29,
        "mindate": "1913-04-01",
        "maxdate": "2025-02-25",
        "latitude": 41.9928,
        "name": "NORTON WEST, MA US",
        "datacoverage": 0.5315,
        "id": "GHCND:USC00195984",
        "elevationUnit": "METERS",
        "longitude": -71.1666
    },
    {
        "elevation": 51.8,
        "mindate": "1967-01-01",
        "maxdate": "1995-03-31",
        "latitude": 42.53333,
        "name": "PEABODY, MA US",
        "datacoverage": 0.976,
        "id": "GHCND:USC00196245",
        "elevationUnit": "METERS",
        "longitude": -70.98333
    },
    {
        "elevation": 64,
        "mindate": "1990-08-01",
        "maxdate": "1996-07-31",
        "latitude": 42.66667,
        "name": "PEPPERELL, MA US",
        "datacoverage": 1,
        "id": "GHCND:USC00196286",
        "elevationUnit": "METERS",
        "longitude": -71.53333
    },
    {
        "elevation": 332.2,
        "mindate": "1913-04-01",
        "maxdate": "1996-12-31",
        "latitude": 42.53333,
        "name": "PETERSHAM 3 N, MA US",
        "datacoverage": 0.8436,
        "id": "GHCND:USC00196322",
        "elevationUnit": "METERS",
        "longitude": -72.18333
    },
    {
        "elevation": 317,
        "mindate": "1894-02-01",
        "maxdate": "1948-12-31",
        "latitude": 42.45,
        "name": "PITTSFIELD, MA US",
        "datacoverage": 0.6423,
        "id": "GHCND:USC00196409",
        "elevationUnit": "METERS",
        "longitude": -73.25
    },
    {
        "elevation": 13.7,
        "mindate": "1893-01-01",
        "maxdate": "2015-07-31",
        "latitude": 41.982,
        "name": "PLYMOUTH KINGSTON, MA US",
        "datacoverage": 0.9646,
        "id": "GHCND:USC00196486",
        "elevationUnit": "METERS",
        "longitude": -70.696
    },
    {
        "elevation": 11.9,
        "mindate": "1893-01-01",
        "maxdate": "1958-04-30",
        "latitude": 42.08333,
        "name": "PROVINCETOWN 3 NW, MA US",
        "datacoverage": 0.9041,
        "id": "GHCND:USC00196676",
        "elevationUnit": "METERS",
        "longitude": -70.21667
    },
    {
        "elevation": 6.1,
        "mindate": "1958-05-01",
        "maxdate": "1992-09-30",
        "latitude": 42.05,
        "name": "PROVINCETOWN, MA US",
        "datacoverage": 0.8365,
        "id": "GHCND:USC00196681",
        "elevationUnit": "METERS",
        "longitude": -70.18333
    },
    {
        "elevation": 202.1,
        "mindate": "1896-01-01",
        "maxdate": "1897-02-28",
        "latitude": 42.37787,
        "name": "QUINAPOXET, MA US",
        "datacoverage": 0.9976,
        "id": "GHCND:USC00196720",
        "elevationUnit": "METERS",
        "longitude": -71.850906
    },
    {
        "elevation": 54.6,
        "mindate": "1886-02-03",
        "maxdate": "1894-12-31",
        "latitude": 42.166667,
        "name": "RANDOLPH, MA US",
        "datacoverage": 0.7686,
        "id": "GHCND:USC00196770",
        "elevationUnit": "METERS",
        "longitude": -71.05
    },
    {
        "elevation": 33.5,
        "mindate": "1960-01-01",
        "maxdate": "2019-12-30",
        "latitude": 42.524,
        "name": "READING, MA US",
        "datacoverage": 0.9927,
        "id": "GHCND:USC00196783",
        "elevationUnit": "METERS",
        "longitude": -71.1249
    },
    {
        "elevation": 22.9,
        "mindate": "1889-12-01",
        "maxdate": "1930-04-30",
        "latitude": 42.366667,
        "name": "ROBERTS DAM, MA US",
        "datacoverage": 0.7464,
        "id": "GHCND:USC00196915",
        "elevationUnit": "METERS",
        "longitude": -71.266667
    },
    {
        "elevation": 19.8,
        "mindate": "1900-01-01",
        "maxdate": "2025-02-25",
        "latitude": 41.7849,
        "name": "ROCHESTER, MA US",
        "datacoverage": 0.5955,
        "id": "GHCND:USC00196938",
        "elevationUnit": "METERS",
        "longitude": -70.9176
    },
    {
        "elevation": 24.1,
        "mindate": "1902-05-01",
        "maxdate": "1983-01-16",
        "latitude": 42.65,
        "name": "ROCKPORT 1 ESE, MA US",
        "datacoverage": 0.9606,
        "id": "GHCND:USC00196977",
        "elevationUnit": "METERS",
        "longitude": -70.6
    },
    {
        "elevation": 487.7,
        "mindate": "1884-11-04",
        "maxdate": "2015-09-30",
        "latitude": 42.7,
        "name": "ROWE, MA US",
        "datacoverage": 0.0344,
        "id": "GHCND:USC00196988",
        "elevationUnit": "METERS",
        "longitude": -72.9
    },
    {
        "elevation": 528.8,
        "mindate": "2015-10-01",
        "maxdate": "2022-10-31",
        "latitude": 42.735,
        "name": "ROWE 3 NE, MA US",
        "datacoverage": 0.9969,
        "id": "GHCND:USC00196989",
        "elevationUnit": "METERS",
        "longitude": -72.8692
    },
    {
        "elevation": 32.6,
        "mindate": "1892-08-01",
        "maxdate": "1901-09-30",
        "latitude": 42.35,
        "name": "ROXBURY, MA US",
        "datacoverage": 0.9232,
        "id": "GHCND:USC00196993",
        "elevationUnit": "METERS",
        "longitude": -71.066667
    },
    {
        "elevation": 308.2,
        "mindate": "1892-06-01",
        "maxdate": "1894-06-30",
        "latitude": 42.677586,
        "name": "ROYALSTON, MA US",
        "datacoverage": 0.3224,
        "id": "GHCND:USC00196996",
        "elevationUnit": "METERS",
        "longitude": -72.18786
    },
    {
        "elevation": 353.6,
        "mindate": "1902-05-01",
        "maxdate": "1929-09-30",
        "latitude": 42.416667,
        "name": "RUTLAND, MA US",
        "datacoverage": 0.8514,
        "id": "GHCND:USC00197104",
        "elevationUnit": "METERS",
        "longitude": -72
    },
    {
        "elevation": 12.2,
        "mindate": "1885-11-01",
        "maxdate": "1909-10-31",
        "latitude": 42.516667,
        "name": "SALEM B, MA US",
        "datacoverage": 0.7884,
        "id": "GHCND:USC00197122",
        "elevationUnit": "METERS",
        "longitude": -70.9
    },
    {
        "elevation": 9.1,
        "mindate": "1948-06-01",
        "maxdate": "1967-02-28",
        "latitude": 42.53333,
        "name": "SALEM COAST GUARD AIR STATION, MA US",
        "datacoverage": 0.7787,
        "id": "GHCND:USC00197124",
        "elevationUnit": "METERS",
        "longitude": -70.86667
    },
    {
        "elevation": 6.1,
        "mindate": "1945-04-01",
        "maxdate": "1968-09-30",
        "latitude": 41.76667,
        "name": "SANDWICH, MA US",
        "datacoverage": 0.974,
        "id": "GHCND:USC00197190",
        "elevationUnit": "METERS",
        "longitude": -70.5
    },
    {
        "elevation": 588.3,
        "mindate": "1999-08-01",
        "maxdate": "2022-04-12",
        "latitude": 42.5691,
        "name": "SAVOY, MA US",
        "datacoverage": 0.164,
        "id": "GHCND:USC00197230",
        "elevationUnit": "METERS",
        "longitude": -72.9955
    },
    {
        "elevation": 73.2,
        "mindate": "1891-05-01",
        "maxdate": "1892-12-31",
        "latitude": 42.683333,
        "name": "SAVOY CENTER, MA US",
        "datacoverage": 0.7856,
        "id": "GHCND:USC00197240",
        "elevationUnit": "METERS",
        "longitude": -73.033333
    },
    {
        "elevation": 11.9,
        "mindate": "1941-05-27",
        "maxdate": "1980-04-30",
        "latitude": 41.83333,
        "name": "SEGREGANSET, MA US",
        "datacoverage": 0.8451,
        "id": "GHCND:USC00197293",
        "elevationUnit": "METERS",
        "longitude": -71.11667
    },
    {
        "elevation": 136.9,
        "mindate": "1930-05-01",
        "maxdate": "1977-05-31",
        "latitude": 42.61667,
        "name": "SHELBURNE FALLS, MA US",
        "datacoverage": 0.9889,
        "id": "GHCND:USC00197370",
        "elevationUnit": "METERS",
        "longitude": -72.73333
    },
    {
        "elevation": 12.2,
        "mindate": "1893-01-01",
        "maxdate": "1922-11-30",
        "latitude": 41.766667,
        "name": "SOMERSET 1, MA US",
        "datacoverage": 0.9909,
        "id": "GHCND:USC00197475",
        "elevationUnit": "METERS",
        "longitude": -71.133333
    },
    {
        "elevation": 208.8,
        "mindate": "1926-03-01",
        "maxdate": "2025-02-25",
        "latitude": 42.0583,
        "name": "SOUTHBRIDGE 3 SW, MA US",
        "datacoverage": 0.9587,
        "id": "GHCND:USC00197627",
        "elevationUnit": "METERS",
        "longitude": -72.0721
    },
    {
        "elevation": 31.1,
        "mindate": "1911-05-01",
        "maxdate": "1958-07-31",
        "latitude": 41.86667,
        "name": "SOUTH CARVER, MA US",
        "datacoverage": 0.2934,
        "id": "GHCND:USC00197643",
        "elevationUnit": "METERS",
        "longitude": -70.71667
    },
    {
        "elevation": 10.1,
        "mindate": "1892-08-04",
        "maxdate": "1894-09-30",
        "latitude": 41.689555,
        "name": "SOUTH DENNIS, MA US",
        "datacoverage": 0.9454,
        "id": "GHCND:USC00197667",
        "elevationUnit": "METERS",
        "longitude": -70.156408
    },
    {
        "elevation": 256,
        "mindate": "1902-03-01",
        "maxdate": "1973-11-08",
        "latitude": 42.15,
        "name": "SOUTH EGREMONT, MA US",
        "datacoverage": 0.7556,
        "id": "GHCND:USC00197692",
        "elevationUnit": "METERS",
        "longitude": -73.45
    },
    {
        "elevation": 24.4,
        "mindate": "1919-05-09",
        "maxdate": "1936-10-15",
        "latitude": 42.05,
        "name": "SOUTH HANSON, MA US",
        "datacoverage": 0.3452,
        "id": "GHCND:USC00197750",
        "elevationUnit": "METERS",
        "longitude": -70.883333
    },
    {
        "elevation": 14.9,
        "mindate": "1966-05-01",
        "maxdate": "1977-12-31",
        "latitude": 41.9,
        "name": "SOUTH WELLFLEET, MA US",
        "datacoverage": 0.9948,
        "id": "GHCND:USC00197961",
        "elevationUnit": "METERS",
        "longitude": -69.98333
    },
    {
        "elevation": 57.9,
        "mindate": "1893-02-01",
        "maxdate": "1984-01-31",
        "latitude": 42.1,
        "name": "SPRINGFIELD, MA US",
        "datacoverage": 0.7951,
        "id": "GHCND:USC00198046",
        "elevationUnit": "METERS",
        "longitude": -72.58333
    },
    {
        "elevation": 36.9,
        "mindate": "1948-08-01",
        "maxdate": "1950-01-31",
        "latitude": 42.1,
        "name": "SPRINGFIELD NEWS BUI, MA US",
        "datacoverage": 0.8871,
        "id": "GHCND:USC00198051",
        "elevationUnit": "METERS",
        "longitude": -72.6
    },
    {
        "elevation": 262.1,
        "mindate": "1929-12-01",
        "maxdate": "2024-12-31",
        "latitude": 42.3,
        "name": "STOCKBRIDGE, MA US",
        "datacoverage": 0.5442,
        "id": "GHCND:USC00198181",
        "elevationUnit": "METERS",
        "longitude": -73.33333
    },
    {
        "elevation": 17.7,
        "mindate": "1929-08-01",
        "maxdate": "1934-01-31",
        "latitude": 42.366667,
        "name": "STONY BROOK, MA US",
        "datacoverage": 0.696,
        "id": "GHCND:USC00198218",
        "elevationUnit": "METERS",
        "longitude": -71.266667
    },
    {
        "elevation": 6.1,
        "mindate": "1929-01-01",
        "maxdate": "1957-02-28",
        "latitude": 42.46667,
        "name": "SWAMPSCOTT, MA US",
        "datacoverage": 0.9711,
        "id": "GHCND:USC00198301",
        "elevationUnit": "METERS",
        "longitude": -70.9
    },
    {
        "elevation": 6.1,
        "mindate": "1893-01-01",
        "maxdate": "2007-09-30",
        "latitude": 41.90028,
        "name": "TAUNTON, MA US",
        "datacoverage": 0.9909,
        "id": "GHCND:USC00198367",
        "elevationUnit": "METERS",
        "longitude": -71.06583
    },
    {
        "elevation": 25.9,
        "mindate": "1994-07-01",
        "maxdate": "2025-02-25",
        "latitude": 41.9561,
        "name": "NWS BOSTON NORTON, MA US",
        "datacoverage": 0.9997,
        "id": "GHCND:USC00198368",
        "elevationUnit": "METERS",
        "longitude": -71.1395
    },
    {
        "elevation": 12.5,
        "mindate": "1885-07-01",
        "maxdate": "1892-12-31",
        "latitude": 41.9,
        "name": "TAUNTON NUMBER 163, MA US",
        "datacoverage": 0.9712,
        "id": "GHCND:USC00198374",
        "elevationUnit": "METERS",
        "longitude": -71.083333
    },
    {
        "elevation": 30.5,
        "mindate": "1884-11-01",
        "maxdate": "1899-04-30",
        "latitude": 41.9,
        "name": "TAUNTON NUMBER 164, MA US",
        "datacoverage": 0.9507,
        "id": "GHCND:USC00198375",
        "elevationUnit": "METERS",
        "longitude": -71.1
    },
    {
        "elevation": 12.2,
        "mindate": "1890-10-01",
        "maxdate": "1896-11-30",
        "latitude": 41.9,
        "name": "TAUNTON NUMBER 184, MA US",
        "datacoverage": 0.7257,
        "id": "GHCND:USC00198376",
        "elevationUnit": "METERS",
        "longitude": -71.1
    },
    {
        "mindate": "1906-01-01",
        "maxdate": "1922-03-31",
        "latitude": 42.316667,
        "name": "THOMPSON S ISLAND, MA US",
        "datacoverage": 0.9651,
        "id": "GHCND:USC00198470",
        "longitude": -71.00611
    },
    {
        "elevation": 207.3,
        "mindate": "1949-07-01",
        "maxdate": "2025-02-25",
        "latitude": 42.6394,
        "name": "TULLY LAKE, MA US",
        "datacoverage": 0.9365,
        "id": "GHCND:USC00198573",
        "elevationUnit": "METERS",
        "longitude": -72.2244
    },
    {
        "elevation": 57.9,
        "mindate": "1892-08-01",
        "maxdate": "1977-08-31",
        "latitude": 42.61667,
        "name": "TURNERS FALLS, MA US",
        "datacoverage": 0.9628,
        "id": "GHCND:USC00198580",
        "elevationUnit": "METERS",
        "longitude": -72.55
    },
    {
        "elevation": 33.5,
        "mindate": "1890-01-01",
        "maxdate": "1897-11-30",
        "latitude": 42.5,
        "name": "WAKEFIELD, MA US",
        "datacoverage": 0.9554,
        "id": "GHCND:USC00198740",
        "elevationUnit": "METERS",
        "longitude": -71.066667
    },
    {
        "elevation": 52.1,
        "mindate": "1948-10-01",
        "maxdate": "1972-06-30",
        "latitude": 42.16667,
        "name": "WALPOLE, MA US",
        "datacoverage": 0.9841,
        "id": "GHCND:USC00198755",
        "elevationUnit": "METERS",
        "longitude": -71.23333
    },
    {
        "elevation": 51.8,
        "mindate": "1972-11-01",
        "maxdate": "2025-02-25",
        "latitude": 42.1609,
        "name": "WALPOLE 2, MA US",
        "datacoverage": 0.9976,
        "id": "GHCND:USC00198757",
        "elevationUnit": "METERS",
        "longitude": -71.2461
    },
    {
        "elevation": 61,
        "mindate": "1951-07-01",
        "maxdate": "1959-04-30",
        "latitude": 42.13333,
        "name": "WALPOLE 1 SSE, MA US",
        "datacoverage": 0.9969,
        "id": "GHCND:USC00198760",
        "elevationUnit": "METERS",
        "longitude": -71.25
    },
    {
        "elevation": 48.8,
        "mindate": "1885-04-01",
        "maxdate": "1895-03-31",
        "latitude": 42.283333,
        "name": "WELLESLEY, MA US",
        "datacoverage": 0.8083,
        "id": "GHCND:USC00198960",
        "elevationUnit": "METERS",
        "longitude": -71.333333
    },
    {
        "elevation": 90.8,
        "mindate": "1893-01-01",
        "maxdate": "1926-03-15",
        "latitude": 42.266667,
        "name": "WESTBORO, MA US",
        "datacoverage": 0.9419,
        "id": "GHCND:USC00199080",
        "elevationUnit": "METERS",
        "longitude": -71.633333
    },
    {
        "elevation": 363,
        "mindate": "1941-02-01",
        "maxdate": "1963-05-31",
        "latitude": 42.48333,
        "name": "WEST CUMMINGTON, MA US",
        "datacoverage": 0.81,
        "id": "GHCND:USC00199136",
        "elevationUnit": "METERS",
        "longitude": -72.96667
    },
    {
        "elevation": 3,
        "mindate": "1976-05-01",
        "maxdate": "1982-12-31",
        "latitude": 41.6,
        "name": "WEST FALMOUTH, MA US",
        "datacoverage": 0.9967,
        "id": "GHCND:USC00199175",
        "elevationUnit": "METERS",
        "longitude": -70.63333
    },
    {
        "elevation": 36.6,
        "mindate": "1926-01-01",
        "maxdate": "1995-11-30",
        "latitude": 42.13333,
        "name": "WESTFIELD, MA US",
        "datacoverage": 0.8651,
        "id": "GHCND:USC00199191",
        "elevationUnit": "METERS",
        "longitude": -72.75
    },
    {
        "elevation": 131.1,
        "mindate": "2007-05-01",
        "maxdate": "2025-02-25",
        "latitude": 42.0931,
        "name": "WESTFIELD 3 SW, MA US",
        "datacoverage": 0.9948,
        "id": "GHCND:USC00199193",
        "elevationUnit": "METERS",
        "longitude": -72.8035
    },
    {
        "elevation": 406,
        "mindate": "1964-05-01",
        "maxdate": "1968-10-31",
        "latitude": 42.08333,
        "name": "WEST GRANVILLE, MA US",
        "datacoverage": 0.969,
        "id": "GHCND:USC00199219",
        "elevationUnit": "METERS",
        "longitude": -72.93333
    },
    {
        "elevation": 326.1,
        "mindate": "1990-09-01",
        "maxdate": "1996-09-30",
        "latitude": 42.06667,
        "name": "WEST GRANVILLE, MA US",
        "datacoverage": 1,
        "id": "GHCND:USC00199221",
        "elevationUnit": "METERS",
        "longitude": -72.93333
    },
    {
        "elevation": 4.6,
        "mindate": "2016-10-25",
        "maxdate": "2021-11-30",
        "latitude": 41.6633,
        "name": "WEST HARWICH, MA US",
        "datacoverage": 0.9946,
        "id": "GHCND:USC00199227",
        "elevationUnit": "METERS",
        "longitude": -70.1161
    },
    {
        "elevation": 36.9,
        "mindate": "1957-03-23",
        "maxdate": "1959-07-31",
        "latitude": 42.46667,
        "name": "WEST LYNN, MA US",
        "datacoverage": 0.9873,
        "id": "GHCND:USC00199289",
        "elevationUnit": "METERS",
        "longitude": -70.96667
    },
    {
        "elevation": 64,
        "mindate": "1957-01-01",
        "maxdate": "2004-12-31",
        "latitude": 42.13333,
        "name": "WEST MEDWAY, MA US",
        "datacoverage": 0.9956,
        "id": "GHCND:USC00199316",
        "elevationUnit": "METERS",
        "longitude": -71.43333
    },
    {
        "elevation": 67.1,
        "mindate": "1896-08-01",
        "maxdate": "1968-06-30",
        "latitude": 42.38333,
        "name": "WESTON, MA US",
        "datacoverage": 0.6833,
        "id": "GHCND:USC00199360",
        "elevationUnit": "METERS",
        "longitude": -71.31667
    },
    {
        "elevation": 394.7,
        "mindate": "1926-03-01",
        "maxdate": "2014-06-17",
        "latitude": 42.1819,
        "name": "WEST OTIS, MA US",
        "datacoverage": 0.8105,
        "id": "GHCND:USC00199371",
        "elevationUnit": "METERS",
        "longitude": -73.2236
    },
    {
        "elevation": 153,
        "mindate": "1950-02-14",
        "maxdate": "1954-12-31",
        "latitude": 42.66667,
        "name": "WILLARD BRK ST FRST, MA US",
        "datacoverage": 0.9747,
        "id": "GHCND:USC00199708",
        "elevationUnit": "METERS",
        "longitude": -71.8
    },
    {
        "elevation": 189.3,
        "mindate": "1999-08-01",
        "maxdate": "2000-11-30",
        "latitude": 42.71556,
        "name": "WILLIAMSTOWN, MA US",
        "datacoverage": 0.998,
        "id": "GHCND:USC00199730",
        "elevationUnit": "METERS",
        "longitude": -73.19222
    },
    {
        "elevation": 216.7,
        "mindate": "1885-01-01",
        "maxdate": "1947-12-31",
        "latitude": 42.716667,
        "name": "WILLIAMSTOWN, MA US",
        "datacoverage": 0.8589,
        "id": "GHCND:USC00199731",
        "elevationUnit": "METERS",
        "longitude": -73.2
    },
    {
        "elevation": 12.2,
        "mindate": "1893-03-01",
        "maxdate": "1895-11-30",
        "latitude": 42.366667,
        "name": "WINTHROP, MA US",
        "datacoverage": 0.9562,
        "id": "GHCND:USC00199820",
        "elevationUnit": "METERS",
        "longitude": -71.983333
    },
    {
        "elevation": 24.4,
        "mindate": "2011-01-01",
        "maxdate": "2021-07-20",
        "latitude": 41.5326,
        "name": "WOODS HOLE GOLF CLUB, MA US",
        "datacoverage": 0.8921,
        "id": "GHCND:USC00199891",
        "elevationUnit": "METERS",
        "longitude": -70.6589
    },
    {
        "elevation": 12.2,
        "mindate": "1964-06-01",
        "maxdate": "1975-07-31",
        "latitude": 41.55,
        "name": "WOODS HOLE 2 NE, MA US",
        "datacoverage": 0.9966,
        "id": "GHCND:USC00199893",
        "elevationUnit": "METERS",
        "longitude": -70.65
    },
    {
        "elevation": 189,
        "mindate": "1892-01-01",
        "maxdate": "1962-10-31",
        "latitude": 42.3,
        "name": "WORCESTER, MA US",
        "datacoverage": 0.9645,
        "id": "GHCND:USC00199928",
        "elevationUnit": "METERS",
        "longitude": -71.81667
    },
    {
        "elevation": 249.9,
        "mindate": "1922-01-01",
        "maxdate": "1930-12-31",
        "latitude": 42.266667,
        "name": "WORCESTER, MA US",
        "datacoverage": 0.3593,
        "id": "GHCND:USC00199929",
        "elevationUnit": "METERS",
        "longitude": -71.833333
    },
    {
        "elevation": 198.1,
        "mindate": "1892-01-01",
        "maxdate": "1900-04-30",
        "latitude": 42.25,
        "name": "WORCESTER C, MA US",
        "datacoverage": 0.7453,
        "id": "GHCND:USC00199936",
        "elevationUnit": "METERS",
        "longitude": -71.75
    },
    {
        "elevation": 391.7,
        "mindate": "1994-06-01",
        "maxdate": "2020-11-30",
        "latitude": 42.3869,
        "name": "WORTHINGTON, MA US",
        "datacoverage": 0.9938,
        "id": "GHCND:USC00199972",
        "elevationUnit": "METERS",
        "longitude": -72.921
    },
    {
        "elevation": 29.6,
        "mindate": "1893-01-01",
        "maxdate": "1938-06-30",
        "latitude": 41.866667,
        "name": "PAWTUCKET, RI US",
        "datacoverage": 0.972,
        "id": "GHCND:USC00375882",
        "elevationUnit": "METERS",
        "longitude": -71.366667
    },
    {
        "elevation": 45.7,
        "mindate": "2003-04-01",
        "maxdate": "2025-02-25",
        "latitude": 41.975,
        "name": "CAPE COD MASSACHUSETTS, MA US",
        "datacoverage": 0.8572,
        "id": "GHCND:USR0000MCAP",
        "elevationUnit": "METERS",
        "longitude": -70.0253
    },
    {
        "elevation": 63.1,
        "mindate": "1958-10-01",
        "maxdate": "1971-07-31",
        "latitude": 42.41667,
        "name": "MAYNARD, MA US",
        "datacoverage": 0.9467,
        "id": "GHCND:USW00004769",
        "elevationUnit": "METERS",
        "longitude": -71.48333
    },
    {
        "elevation": 86.9,
        "mindate": "1960-10-21",
        "maxdate": "1963-09-30",
        "latitude": 42.56667,
        "name": "FORT DEVENS ARMY AIR FIELD, MA US",
        "datacoverage": 0.9507,
        "id": "GHCND:USW00004779",
        "elevationUnit": "METERS",
        "longitude": -71.6
    },
    {
        "elevation": 102.3,
        "mindate": "1997-10-01",
        "maxdate": "2025-02-24",
        "latitude": 42.55495,
        "name": "FITCHBURG MUNICIPAL AIRPORT, MA US",
        "datacoverage": 0.9945,
        "id": "GHCND:USW00004780",
        "elevationUnit": "METERS",
        "longitude": -71.75699
    },
    {
        "elevation": 39,
        "mindate": "1949-01-01",
        "maxdate": "2025-02-24",
        "latitude": 42.46811,
        "name": "BEDFORD HANSCOM FIELD, MA US",
        "datacoverage": 0.6355,
        "id": "GHCND:USW00014702",
        "elevationUnit": "METERS",
        "longitude": -71.29463
    },
    {
        "elevation": 75,
        "mindate": "1942-02-01",
        "maxdate": "1970-12-31",
        "latitude": 42.2,
        "name": "CHICOPEE FALLS WESTOVER FIELD, MA US",
        "datacoverage": 0.9912,
        "id": "GHCND:USW00014703",
        "elevationUnit": "METERS",
        "longitude": -72.53333
    },
    {
        "elevation": 39.6,
        "mindate": "1949-01-01",
        "maxdate": "2010-09-20",
        "latitude": 41.65,
        "name": "FALMOUTH OTIS AFB, MA US",
        "datacoverage": 0.399,
        "id": "GHCND:USW00014704",
        "elevationUnit": "METERS",
        "longitude": -70.51667
    },
    {
        "elevation": 3.2,
        "mindate": "1936-01-01",
        "maxdate": "2025-02-25",
        "latitude": 42.36057,
        "name": "BOSTON LOGAN INTERNATIONAL AIRPORT, MA US",
        "datacoverage": 1,
        "id": "GHCND:USW00014739",
        "elevationUnit": "METERS",
        "longitude": -71.00975
    },
    {
        "elevation": 190.5,
        "mindate": "1998-04-01",
        "maxdate": "2024-09-30",
        "latitude": 42.2123,
        "name": "BLUE HILL LCD, MA US",
        "datacoverage": 0.9765,
        "id": "GHCND:USW00014753",
        "elevationUnit": "METERS",
        "longitude": -71.1137
    },
    {
        "elevation": 11.2,
        "mindate": "1948-01-01",
        "maxdate": "2025-02-24",
        "latitude": 41.25407,
        "name": "NANTUCKET MEMORIAL AIRPORT, MA US",
        "datacoverage": 0.7946,
        "id": "GHCND:USW00014756",
        "elevationUnit": "METERS",
        "longitude": -70.05893
    },
    {
        "elevation": 351.2,
        "mindate": "1925-06-01",
        "maxdate": "2025-02-24",
        "latitude": 42.42686,
        "name": "PITTSFIELD MUNICIPAL AIRPORT, MA US",
        "datacoverage": 0.6728,
        "id": "GHCND:USW00014763",
        "elevationUnit": "METERS",
        "longitude": -73.28907
    },
    {
        "elevation": 80.6,
        "mindate": "1948-06-01",
        "maxdate": "2025-02-24",
        "latitude": 42.16005,
        "name": "WESTFIELD BARNES REGIONAL AIRPORT, MA US",
        "datacoverage": 0.3965,
        "id": "GHCND:USW00014775",
        "elevationUnit": "METERS",
        "longitude": -72.71246
    },
    {
        "elevation": 82,
        "mindate": "1945-03-01",
        "maxdate": "1945-09-30",
        "latitude": 42.56667,
        "name": "AYER, MA US",
        "datacoverage": 1,
        "id": "GHCND:USW00014781",
        "elevationUnit": "METERS",
        "longitude": -71.6
    },
    {
        "elevation": 4.9,
        "mindate": "1945-02-01",
        "maxdate": "1951-12-31",
        "latitude": 42.26667,
        "name": "SQUANTUM NAS, MA US",
        "datacoverage": 0.7762,
        "id": "GHCND:USW00014789",
        "elevationUnit": "METERS",
        "longitude": -71.03333
    },
    {
        "elevation": 49.1,
        "mindate": "1945-04-01",
        "maxdate": "1996-09-28",
        "latitude": 42.15,
        "name": "SOUTH WEYMOUTH NAS, MA US",
        "datacoverage": 0.8367,
        "id": "GHCND:USW00014790",
        "elevationUnit": "METERS",
        "longitude": -70.93333
    },
    {
        "elevation": 13,
        "mindate": "1998-06-06",
        "maxdate": "2025-02-22",
        "latitude": 42.19123,
        "name": "NORWOOD MEMORIAL AIRPORT, MA US",
        "datacoverage": 0.9957,
        "id": "GHCND:USW00054704",
        "elevationUnit": "METERS",
        "longitude": -71.17326
    },
    {
        "elevation": 27.6,
        "mindate": "1998-12-05",
        "maxdate": "2025-02-22",
        "latitude": 42.5841,
        "name": "BEVERLY MUNICIPAL AIRPORT, MA US",
        "datacoverage": 0.9978,
        "id": "GHCND:USW00054733",
        "elevationUnit": "METERS",
        "longitude": -70.9153
    },
    {
        "elevation": 165.8,
        "mindate": "1996-07-01",
        "maxdate": "2025-02-22",
        "latitude": 42.56998,
        "name": "ORANGE MUNICIPAL AIRPORT, MA US",
        "datacoverage": 0.9871,
        "id": "GHCND:USW00054756",
        "elevationUnit": "METERS",
        "longitude": -72.28696
    },
    {
        "elevation": 197,
        "mindate": "1987-10-01",
        "maxdate": "2025-02-22",
        "latitude": 42.69729,
        "name": "NORTH ADAMS HARRIMAN AIRPORT, MA US",
        "datacoverage": 0.7945,
        "id": "GHCND:USW00054768",
        "elevationUnit": "METERS",
        "longitude": -73.1696
    },
    {
        "elevation": 42.2,
        "mindate": "1996-07-06",
        "maxdate": "2025-02-22",
        "latitude": 41.90851,
        "name": "PLYMOUTH MUNICIPAL AIRPORT, MA US",
        "datacoverage": 0.9911,
        "id": "GHCND:USW00054769",
        "elevationUnit": "METERS",
        "longitude": -70.72785
    },
    {
        "elevation": 8.6,
        "mindate": "1997-12-01",
        "maxdate": "2025-02-22",
        "latitude": 41.87561,
        "name": "TAUNTON MUNICIPAL AIRPORT, MA US",
        "datacoverage": 0.9708,
        "id": "GHCND:USW00054777",
        "elevationUnit": "METERS",
        "longitude": -71.02083
    },
    {
        "elevation": 18.5,
        "mindate": "1996-07-01",
        "maxdate": "2025-02-22",
        "latitude": 41.68778,
        "name": "CHATHAM MUNICIPAL AIRPORT, MA US",
        "datacoverage": 0.9907,
        "id": "GHCND:USW00094624",
        "elevationUnit": "METERS",
        "longitude": -69.99318
    },
    {
        "elevation": 6.1,
        "mindate": "1893-01-01",
        "maxdate": "1935-12-31",
        "latitude": 42.35,
        "name": "BOSTON CITY WEATHER SERVICE OFFICE, MA US",
        "datacoverage": 1,
        "id": "GHCND:USW00094701",
        "elevationUnit": "METERS",
        "longitude": -71.06667
    },
    {
        "elevation": 11.4,
        "mindate": "1998-01-01",
        "maxdate": "2025-02-22",
        "latitude": 41.6719,
        "name": "HYANNIS BARNSTABLE MUNICIPAL AIRPORT, MA US",
        "datacoverage": 0.9946,
        "id": "GHCND:USW00094720",
        "elevationUnit": "METERS",
        "longitude": -70.26972
    },
    {
        "elevation": 41.5,
        "mindate": "1997-06-08",
        "maxdate": "2025-02-22",
        "latitude": 42.71249,
        "name": "LAWRENCE MUNICIPAL AIRPORT, MA US",
        "datacoverage": 0.9895,
        "id": "GHCND:USW00094723",
        "elevationUnit": "METERS",
        "longitude": -71.12558
    },
    {
        "elevation": 17.9,
        "mindate": "1998-01-01",
        "maxdate": "2025-02-22",
        "latitude": 41.39296,
        "name": "VINEYARD HAVEN MARTHAS VINEYARD AIRPORT, MA US",
        "datacoverage": 0.9855,
        "id": "GHCND:USW00094724",
        "elevationUnit": "METERS",
        "longitude": -70.61592
    },
    {
        "elevation": 22.4,
        "mindate": "1996-07-01",
        "maxdate": "2025-02-22",
        "latitude": 41.67908,
        "name": "NEW BEDFORD MUNICIPAL AIRPORT, MA US",
        "datacoverage": 0.9907,
        "id": "GHCND:USW00094726",
        "elevationUnit": "METERS",
        "longitude": -70.95911
    },
    {
        "elevation": 305.5,
        "mindate": "1948-06-01",
        "maxdate": "2025-02-23",
        "latitude": 42.2706,
        "name": "WORCESTER REGIONAL AIRPORT, MA US",
        "datacoverage": 0.9998,
        "id": "GHCND:USW00094746",
        "elevationUnit": "METERS",
        "longitude": -71.8731
    }
]